public_api_sdk/__init__.py
public_api_sdk/api_client.py
public_api_sdk/auth_config.py
public_api_sdk/auth_manager.py
public_api_sdk/auth_provider.py
public_api_sdk/exceptions.py
public_api_sdk/order_subscription_manager.py
public_api_sdk/price_stream.py
public_api_sdk/public_api_client.py
public_api_sdk/py.typed
public_api_sdk/subscription_manager.py
public_api_sdk/models/__init__.py
public_api_sdk/models/account.py
public_api_sdk/models/auth.py
public_api_sdk/models/history.py
public_api_sdk/models/instrument.py
public_api_sdk/models/instrument_type.py
public_api_sdk/models/new_order.py
public_api_sdk/models/option.py
public_api_sdk/models/order.py
public_api_sdk/models/portfolio.py
public_api_sdk/models/quote.py
public_api_sdk/models/subscription.py
publicdotcom_py-0.1.8.dist-info/licenses/LICENCE
publicdotcom_py-0.1.8.dist-info/METADATA
publicdotcom_py-0.1.8.dist-info/WHEEL
publicdotcom_py-0.1.8.dist-info/top_level.txt
publicdotcom_py-0.1.8.dist-info/RECORD
