Metadata-Version: 2.4
Name: publicdotcom-py
Version: 0.1.8
Summary: Python SDK for Public.com API
Author-email: Public <api-support@public.com>
License: Apache-2.0
Project-URL: Homepage, https://public.com/api/docs
Project-URL: Repository, https://github.com/PublicDotCom/publicdotcom-py
Project-URL: Issues, https://github.com/PublicDotCom/publicdotcom-py/issues
Keywords: api,sdk,trading,finance
Classifier: Development Status :: 3 - Alpha
Classifier: Intended Audience :: Developers
Classifier: License :: OSI Approved :: Apache Software License
Classifier: Programming Language :: Python :: 3.8
Classifier: Programming Language :: Python :: 3.9
Classifier: Programming Language :: Python :: 3.10
Classifier: Programming Language :: Python :: 3.11
Classifier: Programming Language :: Python :: 3.12
Requires-Python: >=3.8
License-File: LICENCE
Requires-Dist: requests>=2.28.0
Requires-Dist: pydantic>=2.0.0
Requires-Dist: typing-extensions>=4.0.0
Requires-Dist: python-dotenv>=1.0.0
Provides-Extra: dev
Requires-Dist: pytest>=7.0.0; extra == "dev"
Requires-Dist: pytest-cov>=4.0.0; extra == "dev"
Requires-Dist: pytest-asyncio>=0.21.0; extra == "dev"
Requires-Dist: black>=23.0.0; extra == "dev"
Requires-Dist: isort>=5.12.0; extra == "dev"
Requires-Dist: mypy>=1.0.0; extra == "dev"
Requires-Dist: pre-commit>=3.0.0; extra == "dev"
Requires-Dist: httpx>=0.24.0; extra == "dev"
Dynamic: license-file
